cubetoolkit.py
cubetoolkit-0.3.1.dist-info/METADATA
cubetoolkit-0.3.1.dist-info/WHEEL
cubetoolkit-0.3.1.dist-info/entry_points.txt
cubetoolkit-0.3.1.dist-info/top_level.txt
cubetoolkit-0.3.1.dist-info/RECORD
