Metadata-Version: 2.1
Name: cubetoolkit
Version: 0.3.1
Summary: toolkit to works on cubicweb cubes
Home-page: https://github.com/Psycojoker/cubetoolkit
Author: Laurent Peuch
Author-email: cortex@worlddomination.be
License: gplv3+
Keywords: cubicweb
Platform: UNKNOWN
Requires-Dist: argh
Requires-Dist: redbaron
Requires-Dist: requests
Requires-Dist: sphinx
